{
 "name": "VTA",
 "website": "http://www.vtatoken.com",
 "description": "VTA's global defi leads the development of mobile games on the NFT game chain, landing in the game sector, with a new innovative gameplay mechanism, and top-level chain game technology development, allowing players to earn money while playing, point-to-point decentralized transactions, and a sticky mechanism. The scarcity and interest of the token, dedicated to the application of the NFT sector",
 "explorer": "https://bscscan.com/token/0xE9b3A0c3FA87c4EeA9C9301D9b9F0f1E6f2aC9AA",
 "type": "BEP20",
 "symbol": "VTA",
 "decimals": 9,
 "status": "active",
 "id": "0xE9b3A0c3FA87c4EeA9C9301D9b9F0f1E6f2aC9AA"
}